{
	"format_version": "1.12.0",
	"minecraft:geometry": [
		{
			"description": {
				"identifier": "geometry.teripod",
				"texture_width": 128,
				"texture_height": 128,
				"visible_bounds_width": 5,
				"visible_bounds_height": 2.5,
				"visible_bounds_offset": [0, 0.75, 0]
			},
			"bones": [
				{
					"name": "teripod",
					"pivot": [0, 0, 0]
				},
				{
					"name": "body",
					"parent": "teripod",
					"pivot": [0, 5.75, 0]
				},
				{
					"name": "front_body",
					"parent": "body",
					"pivot": [0, 5.25, 0],
					"cubes": [
						{"origin": [-3, 2.5, -9], "size": [6, 2, 9], "uv": [0, 15]},
						{"origin": [-3.5, 3.75, -10], "size": [7, 5, 10], "uv": [0, 0]},
						{"origin": [3.51, 6.35, -3.6], "size": [0, 1, 1], "pivot": [3.51, 6.35, -3.35], "rotation": [-22.5, 0, 0], "uv": [34, 26]},
						{"origin": [3.51, 5.85, -3.6], "size": [0, 1, 1], "pivot": [3.51, 6.35, -3.35], "rotation": [-22.5, 0, 0], "uv": [34, 27]},
						{"origin": [3.51, 5.85, -4.1], "size": [0, 1, 1], "pivot": [3.51, 6.35, -3.35], "rotation": [-22.5, 0, 0], "uv": [32, 27]},
						{"origin": [3.51, 6.35, -4.1], "size": [0, 1, 1], "pivot": [3.51, 6.35, -3.35], "rotation": [-22.5, 0, 0], "uv": [32, 26]},
						{"origin": [3.51, 7.0206, -2.09672], "size": [0, 1, 1], "pivot": [3.51, 7.5206, -1.59672], "rotation": [-40, 0, 0], "uv": [33, 28]},
						{"origin": [-3.51, 6.35, -4.1], "size": [0, 1, 1], "pivot": [-3.51, 6.35, -3.35], "rotation": [-22.5, 0, 0], "uv": [38, 26], "mirror": true},
						{"origin": [-3.51, 6.35, -3.6], "size": [0, 1, 1], "pivot": [-3.51, 6.35, -3.35], "rotation": [-22.5, 0, 0], "uv": [40, 26], "mirror": true},
						{"origin": [-3.51, 5.85, -3.6], "size": [0, 1, 1], "pivot": [-3.51, 6.35, -3.35], "rotation": [-22.5, 0, 0], "uv": [40, 27], "mirror": true},
						{"origin": [-3.51, 5.85, -4.1], "size": [0, 1, 1], "pivot": [-3.51, 6.35, -3.35], "rotation": [-22.5, 0, 0], "uv": [38, 27], "mirror": true},
						{"origin": [-3.51, 7.0206, -2.09672], "size": [0, 1, 1], "pivot": [-3.51, 7.5206, -1.59672], "rotation": [-40, 0, 0], "uv": [39, 28], "mirror": true},
						{"origin": [-2.5, 4.25, -0.75], "size": [5, 4, 2], "uv": [18, 52]},
						{"origin": [-3, 8.25, -9], "size": [6, 1, 9], "uv": [0, 26]}
					]
				},
				{
					"name": "opal_gem",
					"parent": "front_body",
					"pivot": [0, 9.25, -2.75],
					"cubes": [
						{"origin": [-1.5, 8.75, -4.75], "size": [3, 1, 4], "uv": [46, 52]},
						{"origin": [-0.75, 9.769, -4.77], "size": [1, 0, 2], "uv": [80, 13]},
						{"origin": [-0.25, 9.769, -4.77], "size": [1, 0, 2], "uv": [80, 15]},
						{"origin": [-0.25, 8.77, -4.77], "size": [1, 1, 0], "uv": [76, 69]},
						{"origin": [-0.75, 8.77, -4.77], "size": [1, 1, 0], "uv": [60, 80]},
						{"origin": [-1, 9.759, -4.76], "size": [1, 0, 2], "uv": [80, 17]},
						{"origin": [0, 9.759, -4.76], "size": [1, 0, 2], "uv": [80, 21]},
						{"origin": [-1, 8.76, -4.76], "size": [2, 1, 0], "uv": [30, 74]},
						{"origin": [-1, 9.76, -3.25], "size": [2, 0, 1], "uv": [60, 56]}
					]
				},
				{
					"name": "opal_gem_outline",
					"parent": "opal_gem",
					"pivot": [0, 9.45, -2.75],
					"cubes": [
						{"origin": [-2, 9.25, -5.25], "size": [0, 1, 5], "uv": [66, 40]},
						{"origin": [-2, 9.25, -5.25], "size": [4, 1, 0], "uv": [66, 51]},
						{"origin": [-2, 10.25, -5.25], "size": [4, 0, 5], "uv": [34, 47]},
						{"origin": [2, 9.25, -5.25], "size": [0, 1, 5], "uv": [10, 66]},
						{"origin": [-2, 9.25, -0.25], "size": [4, 1, 0], "uv": [76, 50]}
					]
				},
				{
					"name": "left_eye",
					"parent": "front_body",
					"pivot": [3, 6.25, -6.75],
					"cubes": [
						{"origin": [2, 4.25, -8.75], "size": [4, 4, 4], "uv": [0, 36]}
					]
				},
				{
					"name": "left_iris",
					"parent": "left_eye",
					"pivot": [4.5, 6.25, -7.75],
					"cubes": [
						{"origin": [3.5, 4.75, -8.75], "size": [2, 3, 2], "inflate": 0.01, "uv": [68, 74]}
					]
				},
				{
					"name": "left_eyelid",
					"parent": "left_eye",
					"pivot": [4.5, 6.125, -6.75],
					"cubes": [
						{"origin": [3, 5.5, -8.75], "size": [3, 1, 4], "inflate": -0.01, "uv": [32, 52]},
						{"origin": [3, 4.25, -8.75], "size": [3, 4, 4], "inflate": -0.02, "uv": [50, 34]}
					]
				},
				{
					"name": "right_eye",
					"parent": "front_body",
					"pivot": [-3, 6.25, -6.75],
					"cubes": [
						{"origin": [-6, 4.25, -8.75], "size": [4, 4, 4], "uv": [34, 39]}
					]
				},
				{
					"name": "right_iris",
					"parent": "right_eye",
					"pivot": [-4.5, 6.25, -7.75],
					"cubes": [
						{"origin": [-5.5, 4.75, -8.75], "size": [2, 3, 2], "inflate": 0.01, "uv": [38, 75]}
					]
				},
				{
					"name": "right_eyelid",
					"parent": "right_eye",
					"pivot": [-4.5, 6.125, -6.75],
					"cubes": [
						{"origin": [-6, 5.5, -8.75], "size": [3, 1, 4], "inflate": -0.01, "uv": [52, 47]},
						{"origin": [-6, 4.25, -8.75], "size": [3, 4, 4], "inflate": -0.02, "uv": [52, 0]}
					]
				},
				{
					"name": "mouth",
					"parent": "front_body",
					"pivot": [0, 5.5, -10.01],
					"cubes": [
						{"origin": [-3, 5, -10.02], "size": [6, 1, 0], "uv": [34, 14]}
					]
				},
				{
					"name": "left_fang",
					"parent": "mouth",
					"pivot": [1.5, 5.5, -10.03],
					"cubes": [
						{"origin": [0.5, 4.5, -10.03], "size": [2, 1, 0], "uv": [20, 66]},
						{"origin": [1, 4, -10.02], "size": [1, 1, 0], "uv": [68, 14]}
					]
				},
				{
					"name": "right_fang",
					"parent": "mouth",
					"pivot": [-1.5, 5.5, -10.03],
					"cubes": [
						{"origin": [-2.5, 4.5, -10.03], "size": [2, 1, 0], "uv": [72, 69]},
						{"origin": [-2, 4, -10.02], "size": [1, 1, 0], "uv": [34, 74]}
					]
				},
				{
					"name": "mouth_open",
					"parent": "front_body",
					"pivot": [0, 5.25, -9],
					"cubes": [
						{"origin": [-1, 3.75, -9.01], "size": [2, 1, 0], "uv": [44, 80]},
						{"origin": [-1.5, 4.5, -9.005], "size": [3, 2, 0], "uv": [80, 29]}
					]
				},
				{
					"name": "left_claw",
					"parent": "front_body",
					"pivot": [3, 3.75, -9],
					"cubes": [
						{"origin": [2.5, 1.86947, -10.49144], "size": [2, 2, 3], "inflate": 0.01, "pivot": [3, 1.86947, -8.49144], "rotation": [7.5, 0, 0], "uv": [66, 46]},
						{"origin": [2.5, 0, -9.5], "size": [2, 2, 2], "uv": [10, 76]},
						{"origin": [2.5, 0.59131, -10.73539], "size": [2, 3, 2], "pivot": [3, 3.59131, -10.73539], "rotation": [-37.5, 0, 0], "uv": [30, 75]},
						{"origin": [3, 1.34131, -10.7554], "size": [1, 2, 0], "pivot": [3, 3.59131, -10.73539], "rotation": [-37.5, 0, 0], "uv": [64, 40]},
						{"origin": [3.25, 1.59131, -10.7454], "size": [1, 2, 0], "pivot": [3, 3.59131, -10.73539], "rotation": [-37.5, 0, 0], "uv": [18, 76]},
						{"origin": [2.75, 1.59131, -10.7454], "size": [1, 2, 0], "pivot": [3, 3.59131, -10.73539], "rotation": [-37.5, 0, 0], "uv": [78, 3]}
					]
				},
				{
					"name": "left_claw_outline",
					"parent": "left_claw",
					"pivot": [3.5, 1.50459, -9.40326],
					"cubes": [
						{"origin": [2, 1.5318, -14.29637], "size": [3, 0, 1], "pivot": [2, 4.52177, -10.54637], "rotation": [52.5, 0, 0], "uv": [56, 30]},
						{"origin": [2, 1.52177, -14.54637], "size": [3, 0, 1], "pivot": [2, 4.52177, -10.54637], "rotation": [52.5, 0, 0], "uv": [8, 44]},
						{"origin": [2, 1.52177, -14.54637], "size": [3, 3, 0], "pivot": [2, 4.52177, -10.54637], "rotation": [52.5, 0, 0], "uv": [0, 80]},
						{"origin": [5, 1.52177, -14.54637], "size": [0, 3, 4], "pivot": [5, 4.52177, -10.54637], "rotation": [52.5, 0, 0], "uv": [20, 67]},
						{"origin": [5, 1.86947, -10.24144], "size": [0, 3, 3], "pivot": [6, 2.36947, -7.74144], "rotation": [7.5, 0, 0], "uv": [76, 34]},
						{"origin": [5, -0.06099, -9.18046], "size": [0, 2, 2], "uv": [10, 60]},
						{"origin": [4.99, -0.06099, -9.93046], "size": [0, 2, 1], "uv": [8, 77]},
						{"origin": [2, -0.051, -9.93046], "size": [3, 0, 1], "uv": [0, 44]},
						{"origin": [2, -0.06099, -9.18046], "size": [3, 0, 2], "uv": [72, 67]},
						{"origin": [2, -0.06099, -9.93046], "size": [3, 1, 0], "uv": [46, 14]},
						{"origin": [2, -0.06099, -9.18046], "size": [0, 2, 2], "uv": [56, 71]},
						{"origin": [2, 1.52177, -14.54637], "size": [0, 3, 4], "pivot": [2, 4.52177, -10.54637], "rotation": [52.5, 0, 0], "uv": [66, 56]},
						{"origin": [2.01, -0.06099, -9.93046], "size": [0, 2, 1], "uv": [68, 11]},
						{"origin": [2, 1.86947, -10.24144], "size": [0, 3, 3], "pivot": [3, 2.36947, -7.74144], "rotation": [7.5, 0, 0], "uv": [54, 75]},
						{"origin": [2, 4.52177, -14.54637], "size": [3, 0, 4], "pivot": [2, 4.52177, -10.54637], "rotation": [52.5, 0, 0], "uv": [32, 57]},
						{"origin": [2, 4.86947, -10.24144], "size": [3, 0, 3], "pivot": [3, 2.36947, -7.74144], "rotation": [7.5, 0, 0], "uv": [68, 8]},
						{"origin": [2, 1.86947, -7.24144], "size": [3, 3, 0], "pivot": [6, 2.36947, -7.74144], "rotation": [7.5, 0, 0], "uv": [80, 3]},
						{"origin": [2, -0.06099, -7.18046], "size": [3, 2, 0], "uv": [66, 63]}
					]
				},
				{
					"name": "right_claw",
					"parent": "front_body",
					"pivot": [-3, 3.75, -9],
					"cubes": [
						{"origin": [-4.5, 1.86947, -10.49144], "size": [2, 2, 3], "inflate": 0.01, "pivot": [-3, 1.86947, -8.49144], "rotation": [7.5, 0, 0], "uv": [70, 26]},
						{"origin": [-4.5, 0, -9.5], "size": [2, 2, 2], "uv": [76, 40]},
						{"origin": [-4.5, 0.59131, -10.73539], "size": [2, 3, 2], "pivot": [-3, 3.59131, -10.73539], "rotation": [-37.5, 0, 0], "uv": [46, 75]},
						{"origin": [-4, 1.34131, -10.7554], "size": [1, 2, 0], "pivot": [-3, 3.59131, -10.73539], "rotation": [-37.5, 0, 0], "uv": [48, 80]},
						{"origin": [-4.25, 1.59131, -10.7454], "size": [1, 2, 0], "pivot": [-3, 3.59131, -10.73539], "rotation": [-37.5, 0, 0], "uv": [50, 80]},
						{"origin": [-3.75, 1.59131, -10.7454], "size": [1, 2, 0], "pivot": [-3, 3.59131, -10.73539], "rotation": [-37.5, 0, 0], "uv": [52, 80]}
					]
				},
				{
					"name": "right_claw_outline",
					"parent": "right_claw",
					"pivot": [-3.5, 1.50459, -9.40326],
					"cubes": [
						{"origin": [-5, 1.5318, -14.29637], "size": [3, 0, 1], "pivot": [-2, 4.52177, -10.54637], "rotation": [52.5, 0, 0], "uv": [78, 73]},
						{"origin": [-5, 1.52177, -14.54637], "size": [3, 0, 1], "pivot": [-2, 4.52177, -10.54637], "rotation": [52.5, 0, 0], "uv": [6, 80]},
						{"origin": [-5, 1.52177, -14.54637], "size": [3, 3, 0], "pivot": [-2, 4.52177, -10.54637], "rotation": [52.5, 0, 0], "uv": [80, 6]},
						{"origin": [-5, 1.52177, -14.54637], "size": [0, 3, 4], "pivot": [-5, 4.52177, -10.54637], "rotation": [52.5, 0, 0], "uv": [28, 67]},
						{"origin": [-5, 1.86947, -10.24144], "size": [0, 3, 3], "pivot": [-6, 2.36947, -7.74144], "rotation": [7.5, 0, 0], "uv": [76, 44]},
						{"origin": [-5, -0.06099, -9.18046], "size": [0, 2, 2], "uv": [14, 80]},
						{"origin": [-4.99, -0.06099, -9.93046], "size": [0, 2, 1], "uv": [74, 79]},
						{"origin": [-5, -0.051, -9.93046], "size": [3, 0, 1], "uv": [80, 9]},
						{"origin": [-5, -0.06099, -9.18046], "size": [3, 0, 2], "uv": [76, 74]},
						{"origin": [-5, -0.06099, -9.93046], "size": [3, 1, 0], "uv": [64, 30]},
						{"origin": [-2, -0.06099, -9.18046], "size": [0, 2, 2], "uv": [80, 23]},
						{"origin": [-2, 1.52177, -14.54637], "size": [0, 3, 4], "pivot": [-2, 4.52177, -10.54637], "rotation": [52.5, 0, 0], "uv": [60, 70]},
						{"origin": [-2.01, -0.06099, -9.93046], "size": [0, 2, 1], "uv": [42, 80]},
						{"origin": [-2, 1.86947, -10.24144], "size": [0, 3, 3], "pivot": [-3, 2.36947, -7.74144], "rotation": [7.5, 0, 0], "uv": [76, 76]},
						{"origin": [-5, 4.52177, -14.54637], "size": [3, 0, 4], "pivot": [-2, 4.52177, -10.54637], "rotation": [52.5, 0, 0], "uv": [60, 52]},
						{"origin": [-5, 4.86947, -10.24144], "size": [3, 0, 3], "pivot": [-3, 2.36947, -7.74144], "rotation": [7.5, 0, 0], "uv": [70, 31]},
						{"origin": [-5, 1.86947, -7.24144], "size": [3, 3, 0], "pivot": [-6, 2.36947, -7.74144], "rotation": [7.5, 0, 0], "uv": [80, 10]},
						{"origin": [-5, -0.06099, -7.18046], "size": [3, 2, 0], "uv": [80, 27]}
					]
				},
				{
					"name": "mid_body",
					"parent": "body",
					"pivot": [0, 5, -1],
					"cubes": [
						{"origin": [-1, 8.21, -0.3], "size": [2, 1, 2], "uv": [60, 77]},
						{"origin": [-1, 7.76, 1.2], "size": [2, 1, 1], "uv": [80, 19]},
						{"origin": [-3, 8.25, -0.26], "size": [6, 1, 2], "inflate": -0.05, "uv": [52, 12]},
						{"origin": [-3.5, 3.75, -0.25], "size": [7, 5, 3], "inflate": -0.01, "uv": [30, 31]},
						{"origin": [-3, 2.5, -0.25], "size": [6, 2, 3], "inflate": -0.05, "uv": [0, 50]}
					]
				},
				{
					"name": "front_left_leg",
					"parent": "mid_body",
					"pivot": [2.8, 3.4, 0.15],
					"cubes": [
						{"origin": [2.5, 1.5, -0.85], "size": [3, 3, 3], "pivot": [4, 3, 0.65], "rotation": [0, 0, 22.5], "uv": [24, 61]},
						{"origin": [2, 2, -0.35], "size": [1, 2, 2], "pivot": [4, 3, 0.65], "rotation": [0, 0, 22.5], "uv": [18, 78]},
						{"origin": [4.8, 0.65, -0.35], "size": [3, 2, 2], "pivot": [6.3, 2.15, 0.15], "rotation": [0, 0, 37.5], "uv": [20, 74]}
					]
				},
				{
					"name": "front_right_leg",
					"parent": "mid_body",
					"pivot": [-2.8, 3.4, 0.15],
					"cubes": [
						{"origin": [-5.5, 1.5, -0.85], "size": [3, 3, 3], "pivot": [-4, 3, 0.65], "rotation": [0, 0, -22.5], "uv": [36, 65]},
						{"origin": [-3, 2, -0.35], "size": [1, 2, 2], "pivot": [-4, 3, 0.65], "rotation": [0, 0, -22.5], "uv": [78, 69]},
						{"origin": [-7.8, 0.65, -0.35], "size": [3, 2, 2], "pivot": [-6.3, 2.15, 0.15], "rotation": [0, 0, -37.5], "uv": [74, 55]}
					]
				},
				{
					"name": "rear_body",
					"parent": "mid_body",
					"pivot": [0, 5.25, 2.5],
					"cubes": [
						{"origin": [-3, 3.75, 2.5], "size": [6, 4, 3], "inflate": -0.02, "uv": [34, 0]},
						{"origin": [-2.5, 7.25, 2.5], "size": [5, 1, 3], "inflate": -0.01, "uv": [52, 8]},
						{"origin": [-1, 7.25, 3.4], "size": [2, 1, 2], "uv": [78, 0]},
						{"origin": [-2.5, 2.6, 2.5], "size": [5, 2, 3], "inflate": -0.01, "uv": [50, 42]}
					]
				},
				{
					"name": "left_antenna_start",
					"parent": "rear_body",
					"pivot": [2, 8.25, 4.5],
					"cubes": [
						{"origin": [1.5, 8.25, 4.5], "size": [1, 0, 3], "uv": [24, 58]}
					]
				},
				{
					"name": "left_antenna2",
					"parent": "left_antenna_start",
					"pivot": [2, 8.25, 7.5],
					"cubes": [
						{"origin": [1.5, 8.25, 7.5], "size": [1, 0, 4], "uv": [68, 70]}
					]
				},
				{
					"name": "left_antenna3",
					"parent": "left_antenna2",
					"pivot": [2, 8.25, 11.5],
					"cubes": [
						{"origin": [1.5, 8.25, 11.5], "size": [1, 0, 4], "uv": [36, 71]}
					]
				},
				{
					"name": "left_antenna4",
					"parent": "left_antenna3",
					"pivot": [2, 8.25, 15.5],
					"cubes": [
						{"origin": [1.5, 8.25, 15.5], "size": [1, 0, 5], "uv": [60, 65]}
					]
				},
				{
					"name": "left_antenna5",
					"parent": "left_antenna4",
					"pivot": [2, 8.25, 20.5],
					"cubes": [
						{"origin": [1.5, 8.25, 20.5], "size": [1, 0, 4], "uv": [46, 71]}
					]
				},
				{
					"name": "left_antennae_end",
					"parent": "left_antenna5",
					"pivot": [2, 8.25, 24.5],
					"cubes": [
						{"origin": [1, 6.25, 24.75], "size": [2, 2, 3], "inflate": -0.25, "uv": [0, 68]},
						{"origin": [1, 6.75, 26.25], "size": [2, 2, 3], "inflate": -0.26, "uv": [70, 11]},
						{"origin": [1, 6, 24.5], "size": [2, 3, 0], "uv": [14, 55]},
						{"origin": [1, 9, 24.5], "size": [2, 0, 5], "uv": [0, 55]},
						{"origin": [1, 6, 29.5], "size": [2, 3, 0], "uv": [30, 80]},
						{"origin": [1, 6, 24.5], "size": [2, 0, 5], "uv": [56, 15]},
						{"origin": [1, 6, 24.5], "size": [0, 3, 5], "uv": [46, 57]},
						{"origin": [3, 6, 24.5], "size": [0, 3, 5], "uv": [56, 57]}
					]
				},
				{
					"name": "right_antenna_start",
					"parent": "rear_body",
					"pivot": [-2, 8.25, 4.5],
					"cubes": [
						{"origin": [-2.5, 8.25, 4.5], "size": [1, 0, 3], "uv": [0, 77]}
					]
				},
				{
					"name": "right_antenna2",
					"parent": "right_antenna_start",
					"pivot": [-2, 8.25, 7.5],
					"cubes": [
						{"origin": [-2.5, 8.25, 7.5], "size": [1, 0, 4], "uv": [10, 72]}
					]
				},
				{
					"name": "right_antenna3",
					"parent": "right_antenna2",
					"pivot": [-2, 8.25, 11.5],
					"cubes": [
						{"origin": [-2.5, 8.25, 11.5], "size": [1, 0, 4], "uv": [72, 63]}
					]
				},
				{
					"name": "right_antenna4",
					"parent": "right_antenna3",
					"pivot": [-2, 8.25, 15.5],
					"cubes": [
						{"origin": [-2.5, 8.25, 15.5], "size": [1, 0, 5], "uv": [66, 0]}
					]
				},
				{
					"name": "right_antenna5",
					"parent": "right_antenna4",
					"pivot": [-2, 8.25, 20.5],
					"cubes": [
						{"origin": [-2.5, 8.25, 20.5], "size": [1, 0, 4], "uv": [0, 73]}
					]
				},
				{
					"name": "right_antennae_end",
					"parent": "right_antenna5",
					"pivot": [-2, 8.25, 24.5],
					"cubes": [
						{"origin": [-3, 6.25, 24.75], "size": [2, 2, 3], "inflate": -0.25, "uv": [70, 16]},
						{"origin": [-3, 6.75, 26.25], "size": [2, 2, 3], "inflate": -0.26, "uv": [70, 21]},
						{"origin": [-3, 6, 24.5], "size": [2, 3, 0], "uv": [34, 80]},
						{"origin": [-3, 9, 24.5], "size": [2, 0, 5], "uv": [56, 20]},
						{"origin": [-3, 6, 29.5], "size": [2, 3, 0], "uv": [38, 80]},
						{"origin": [-3, 6, 24.5], "size": [2, 0, 5], "uv": [56, 25]},
						{"origin": [-1, 6, 24.5], "size": [0, 3, 5], "uv": [14, 58]},
						{"origin": [-3, 6, 24.5], "size": [0, 3, 5], "uv": [0, 60]}
					]
				},
				{
					"name": "back_left_leg",
					"parent": "rear_body",
					"pivot": [2.3, 3.4, 3.65],
					"cubes": [
						{"origin": [2, 1.5, 2.65], "size": [3, 3, 3], "pivot": [3.5, 3, 4.15], "rotation": [0, 0, 22.5], "uv": [64, 34]},
						{"origin": [1.5, 2, 3.15], "size": [1, 2, 2], "pivot": [3.5, 3, 4.15], "rotation": [0, 0, 22.5], "uv": [24, 78]},
						{"origin": [4.3, 0.65, 3.15], "size": [3, 2, 2], "pivot": [5.8, 2.15, 3.65], "rotation": [0, 0, 37.5], "uv": [74, 51]}
					]
				},
				{
					"name": "back_right_leg",
					"parent": "rear_body",
					"pivot": [-2.3, 3.4, 3.65],
					"cubes": [
						{"origin": [-5, 1.5, 2.65], "size": [3, 3, 3], "pivot": [-3.5, 3, 4.15], "rotation": [0, 0, -22.5], "uv": [48, 65]},
						{"origin": [-2.5, 2, 3.15], "size": [1, 2, 2], "pivot": [-3.5, 3, 4.15], "rotation": [0, 0, -22.5], "uv": [68, 79]},
						{"origin": [-7.3, 0.65, 3.15], "size": [3, 2, 2], "pivot": [-5.8, 2.15, 3.65], "rotation": [0, 0, -37.5], "uv": [74, 59]}
					]
				},
				{
					"name": "tail_start",
					"parent": "rear_body",
					"pivot": [0, 3.75, 5.5],
					"cubes": [
						{"origin": [-2.5, 6.25, 5.25], "size": [5, 1, 4], "inflate": -0.01, "uv": [0, 45]},
						{"origin": [-0.5, 6.25, 7.4], "size": [1, 1, 1], "uv": [10, 64]},
						{"origin": [-2.5, 3.75, 5.5], "size": [5, 3, 4], "uv": [34, 7]},
						{"origin": [-2.5, 2.75, 5.25], "size": [5, 2, 4], "inflate": -0.02, "uv": [16, 39]},
						{"origin": [-3.5, 4.25, 6.5], "size": [7, 0, 3], "uv": [50, 31]}
					]
				},
				{
					"name": "tail_end",
					"parent": "tail_start",
					"pivot": [0, 4.25, 9.5],
					"cubes": [
						{"origin": [-2, 3, 8.75], "size": [4, 3, 4], "uv": [18, 45]},
						{"origin": [-1.5, 3.25, 12.75], "size": [3, 2, 2], "uv": [36, 61]},
						{"origin": [-4.5, 4.25, 9.5], "size": [4, 0, 3], "uv": [66, 5]},
						{"origin": [0.5, 4.25, 9.5], "size": [4, 0, 3], "uv": [16, 36]},
						{"origin": [-1.5, 4.26, 9.5], "size": [6, 0, 12], "pivot": [4.5, 4.251, 9.5], "rotation": [0, 27.5, 0], "uv": [31, 15]},
						{"origin": [-4.5, 4.26, 9.5], "size": [6, 0, 12], "pivot": [-4.5, 4.251, 9.5], "rotation": [0, -27.5, 0], "uv": [19, 15]}
					]
				}
			]
		}
	]
}